{
  "last_updated": "2025-10-31T07:14:00.750502Z",
  "source_url": "https://data.bzerox.org/mainnet/",
  "alternative_source_url": "https://b0x-token.github.io/B0x_scripts_auto/mainnetB0x/",
  "primary_available": true,
  "alternative_available": true,
  "stats": {
    "downloaded": 0,
    "updated": 8,
    "errors": 0,
    "skipped": 1
  },
  "files": [
    {
      "path": "RichList_RightsTo0xBTC_MainnetETH_holders.json",
      "size": 613,
      "modified": "2025-10-31T07:14:00.402507Z",
      "md5": "44ec32492be177c895fea89f23859cab"
    },
    {
      "path": "mined_blocks_testnet.json",
      "size": 278126,
      "modified": "2025-10-31T07:13:54.612311Z",
      "md5": "ec38b30e891cf22ec21ad931cfd3bb82"
    },
    {
      "path": "testnet_uniswap_v4_data.json",
      "size": 6576,
      "modified": "2025-10-31T07:14:00.554508Z",
      "md5": "e7b7c8f4fdfca1c9d82edbf83609ebaa"
    },
    {
      "path": "price_data_bwork.json",
      "size": 6660,
      "modified": "2025-10-31T07:14:00.498507Z",
      "md5": "a7d56026c6a44d001967544344a92bb2"
    },
    {
      "path": "mined_blocks_testnet.js",
      "size": 354,
      "modified": "2025-10-31T07:13:54.611311Z",
      "md5": "04f660f0973f48b1fa99b58e20d0b82d"
    },
    {
      "path": "RichList_B0x_testnet.json",
      "size": 2055,
      "modified": "2025-10-31T07:14:00.364507Z",
      "md5": "ed686d80049222036a1b3fe8ddad68c9"
    },
    {
      "path": "RichList_B0x_testnet_miners.json",
      "size": 275,
      "modified": "2025-10-31T07:14:00.383507Z",
      "md5": "be0fa5f8b613db4be642166617e08ccd"
    },
    {
      "path": "atestnet_uniswap_v4_data.json",
      "size": 1084,
      "modified": "2025-10-31T07:13:54.611311Z",
      "md5": "fecdd4dea02d9e8cb3600ae50776b9e2"
    },
    {
      "path": "B0x_Staking_Rich_List_logs_testnet.json",
      "size": 573,
      "modified": "2025-10-31T07:14:00.341507Z",
      "md5": "5a12ba4751c71f4e1f1336cff0bfc2b8"
    },
    {
      "path": "uniswap_v4_data_testnet.json",
      "size": 2353,
      "modified": "2025-10-31T07:13:54.612311Z",
      "md5": "cc51aadbda45ff461a7b4d6f21aa620b"
    },
    {
      "path": "RichList__MainnetETH_holders.json",
      "size": 452,
      "modified": "2025-10-31T07:14:00.424507Z",
      "md5": "55ef167e6767ce54c5df1cd19829ef84"
    },
    {
      "path": "githubERC20RewardsTestnet.json",
      "size": 182,
      "modified": "2025-10-31T07:13:54.611311Z",
      "md5": "f4559b4fa75caf8238c951742f6506a2"
    },
    {
      "path": "uu_mined_blocks_testnet.json",
      "size": 415060,
      "modified": "2025-10-31T07:14:00.748509Z",
      "md5": "2b1ba28a75f60fecf33d353da4940a4b"
    }
  ]
}