{
  "last_updated": "2025-09-25T05:50:01.049505Z",
  "source_url": "https://data.bzerox.org/mainnet/",
  "stats": {
    "downloaded": 0,
    "updated": 5,
    "errors": 0,
    "skipped": 4
  },
  "files": [
    {
      "path": "RichList_RightsTo0xBTC_MainnetETH_holders.json",
      "size": 459,
      "modified": "2025-09-25T05:50:00.767171Z",
      "md5": "8215d903c1053708f23991e6f4630ed9"
    },
    {
      "path": "mined_blocks_testnet.json",
      "size": 278126,
      "modified": "2025-09-25T05:49:55.440110Z",
      "md5": "ec38b30e891cf22ec21ad931cfd3bb82"
    },
    {
      "path": "testnet_uniswap_v4_data.json",
      "size": 2355,
      "modified": "2025-09-25T05:50:00.989172Z",
      "md5": "061b527aaa8f6c608c6bf44288a0928b"
    },
    {
      "path": "price_data_bwork.json",
      "size": 6807,
      "modified": "2025-09-25T05:49:55.440110Z",
      "md5": "54247b396f7bd75b09d83bc169df06b4"
    },
    {
      "path": "mined_blocks_testnet.js",
      "size": 354,
      "modified": "2025-09-25T05:49:55.439110Z",
      "md5": "04f660f0973f48b1fa99b58e20d0b82d"
    },
    {
      "path": "RichList_B0x_testnet.json",
      "size": 927,
      "modified": "2025-09-25T05:50:00.662171Z",
      "md5": "7e35a6c45afdb024eef1941b93992f00"
    },
    {
      "path": "RichList_B0x_testnet_miners.json",
      "size": 269,
      "modified": "2025-09-25T05:50:00.715171Z",
      "md5": "c1a7fe6d91e0a6167543255df6b8ff9b"
    },
    {
      "path": "atestnet_uniswap_v4_data.json",
      "size": 1084,
      "modified": "2025-09-25T05:49:55.439110Z",
      "md5": "fecdd4dea02d9e8cb3600ae50776b9e2"
    },
    {
      "path": "B0x_Staking_Rich_List_logs_testnet.json",
      "size": 318,
      "modified": "2025-09-25T05:49:55.439110Z",
      "md5": "91e0195de46819b3461b0ee466dab217"
    },
    {
      "path": "RichList__MainnetETH_holders.json",
      "size": 601,
      "modified": "2025-09-25T05:50:00.827171Z",
      "md5": "39ce4c553935dac319129b041ec1d19d"
    },
    {
      "path": "githubERC20RewardsTestnet.json",
      "size": 182,
      "modified": "2025-09-25T05:49:55.439110Z",
      "md5": "f4559b4fa75caf8238c951742f6506a2"
    },
    {
      "path": "uu_mined_blocks_testnet.json",
      "size": 294,
      "modified": "2025-09-25T05:49:55.440110Z",
      "md5": "8d3665fe07dd9792df547ba913904a91"
    }
  ]
}