{
  "last_updated": "2025-11-02T08:57:00.761118Z",
  "source_url": "https://data.bzerox.org/mainnet/",
  "alternative_source_url": "https://b0x-token.github.io/B0x_scripts_auto/mainnetB0x/",
  "primary_available": true,
  "alternative_available": true,
  "stats": {
    "downloaded": 0,
    "updated": 7,
    "errors": 0,
    "skipped": 2
  },
  "files": [
    {
      "path": "RichList_RightsTo0xBTC_MainnetETH_holders.json",
      "size": 613,
      "modified": "2025-11-02T08:56:59.698970Z",
      "md5": "e7d24377d3c8fdd723aded908e1d4588"
    },
    {
      "path": "mined_blocks_testnet.json",
      "size": 278126,
      "modified": "2025-11-02T08:56:52.973934Z",
      "md5": "ec38b30e891cf22ec21ad931cfd3bb82"
    },
    {
      "path": "testnet_uniswap_v4_data.json",
      "size": 7782,
      "modified": "2025-11-02T08:57:00.168972Z",
      "md5": "5cc75d792236efb7305181c7e36eae52"
    },
    {
      "path": "price_data_bwork.json",
      "size": 6717,
      "modified": "2025-11-02T08:57:00.002971Z",
      "md5": "f7c04425f833ab7f2b60d6f08c1c4286"
    },
    {
      "path": "mined_blocks_testnet.js",
      "size": 354,
      "modified": "2025-11-02T08:56:52.972934Z",
      "md5": "04f660f0973f48b1fa99b58e20d0b82d"
    },
    {
      "path": "RichList_B0x_testnet.json",
      "size": 21190,
      "modified": "2025-11-02T08:56:59.557970Z",
      "md5": "4081eb135ef06ef5c8b48a990d814388"
    },
    {
      "path": "RichList_B0x_testnet_miners.json",
      "size": 21986,
      "modified": "2025-11-02T08:56:59.630970Z",
      "md5": "d3c492c952f15ed6614e8940cfaeec8c"
    },
    {
      "path": "atestnet_uniswap_v4_data.json",
      "size": 1084,
      "modified": "2025-11-02T08:56:52.972934Z",
      "md5": "fecdd4dea02d9e8cb3600ae50776b9e2"
    },
    {
      "path": "B0x_Staking_Rich_List_logs_testnet.json",
      "size": 1073,
      "modified": "2025-11-02T08:56:52.971934Z",
      "md5": "0b4e66bf3944aedfa34ba746819608f6"
    },
    {
      "path": "uniswap_v4_data_testnet.json",
      "size": 2353,
      "modified": "2025-11-02T08:56:52.973934Z",
      "md5": "cc51aadbda45ff461a7b4d6f21aa620b"
    },
    {
      "path": "RichList__MainnetETH_holders.json",
      "size": 452,
      "modified": "2025-11-02T08:56:59.770971Z",
      "md5": "994d5689352163498509ed59186161f7"
    },
    {
      "path": "githubERC20RewardsTestnet.json",
      "size": 182,
      "modified": "2025-11-02T08:56:52.972934Z",
      "md5": "f4559b4fa75caf8238c951742f6506a2"
    },
    {
      "path": "uu_mined_blocks_testnet.json",
      "size": 1277369,
      "modified": "2025-11-02T08:57:00.757974Z",
      "md5": "466f2aee7b3b36d79ea830fcd84cf6e8"
    }
  ]
}