{
  "last_updated": "2025-11-30T08:20:51.636504Z",
  "source_url": "https://data.bzerox.org/mainnet/",
  "alternative_source_url": "https://b0x-token.github.io/B0x_scripts_auto/mainnetB0x/",
  "primary_available": true,
  "alternative_available": true,
  "stats": {
    "downloaded": 0,
    "updated": 10,
    "errors": 0,
    "skipped": 7
  },
  "files": [
    {
      "path": "RichList_RightsTo0xBTC_MainnetETH_holders.json",
      "size": 613,
      "modified": "2025-11-30T08:20:45.027291Z",
      "md5": "688b75a9bfbe0c932e1b46b722db9ab8"
    },
    {
      "path": "mined_blocks_testnet.json",
      "size": 278126,
      "modified": "2025-11-30T08:20:45.036291Z",
      "md5": "ec38b30e891cf22ec21ad931cfd3bb82"
    },
    {
      "path": "testnet_uniswap_v4_data.json",
      "size": 12606,
      "modified": "2025-11-30T08:20:45.036291Z",
      "md5": "07e66202c02f9f678589db09503a223f"
    },
    {
      "path": "price_data_bwork.json",
      "size": 5104,
      "modified": "2025-11-30T08:20:51.255298Z",
      "md5": "a4bf59ce13124f6e6e58189c88c691fe"
    },
    {
      "path": "mined_blocks_testnet.js",
      "size": 354,
      "modified": "2025-11-30T08:20:45.035291Z",
      "md5": "04f660f0973f48b1fa99b58e20d0b82d"
    },
    {
      "path": "RichList_B0x_testnet.json",
      "size": 23229,
      "modified": "2025-11-30T08:20:45.027291Z",
      "md5": "38bfddf555d337ad0c957cd4dc8b9a06"
    },
    {
      "path": "RichList_B0x_mainnet_miners.json",
      "size": 6548,
      "modified": "2025-11-30T08:20:50.561295Z",
      "md5": "22b52d31c8046144832c17fa6adc1cf7"
    },
    {
      "path": "RichList_B0x_testnet_miners.json",
      "size": 24855,
      "modified": "2025-11-30T08:20:45.027291Z",
      "md5": "0444b8e93f71d6307837ac6dc166c973"
    },
    {
      "path": "price_data_bwork_mainnet.json",
      "size": 6719,
      "modified": "2025-11-30T08:20:51.299299Z",
      "md5": "45368fc4223b9bce5c77d2d413208dba"
    },
    {
      "path": "atestnet_uniswap_v4_data.json",
      "size": 1084,
      "modified": "2025-11-30T08:20:45.028291Z",
      "md5": "fecdd4dea02d9e8cb3600ae50776b9e2"
    },
    {
      "path": "RichList_RightsTo0xBTC_mainnet_ETH_holders.json",
      "size": 765,
      "modified": "2025-11-30T08:20:50.731296Z",
      "md5": "7407da3120f94b20c06dc2f64943e1a6"
    },
    {
      "path": "B0x_Staking_Rich_List_logs_testnet.json",
      "size": 1975,
      "modified": "2025-11-30T08:20:45.027291Z",
      "md5": "0de0ce2d7e784eb9b675c448cdbf7b61"
    },
    {
      "path": "RichList_B0x_mainnet.json",
      "size": 23941,
      "modified": "2025-11-30T08:20:50.517294Z",
      "md5": "7ac2b30539f7cc562cebee59543061d5"
    },
    {
      "path": "mined_blocks_mainnet.json",
      "size": 1903877,
      "modified": "2025-11-30T08:20:51.190298Z",
      "md5": "ee410af78614a2c3c2c1c61a7585c185"
    },
    {
      "path": "RichList__Mainnet_ETH_holders.json",
      "size": 907,
      "modified": "2025-11-30T08:20:50.807296Z",
      "md5": "3a5f186f30f9be7563cc5896b3a63ed8"
    },
    {
      "path": "mainnet_uniswap_v4_data.json",
      "size": 30698,
      "modified": "2025-11-30T08:20:50.890296Z",
      "md5": "1ee88aed8124620f430b297c018cf5d9"
    },
    {
      "path": "uniswap_v4_data_testnet.json",
      "size": 2353,
      "modified": "2025-11-30T08:20:45.036291Z",
      "md5": "cc51aadbda45ff461a7b4d6f21aa620b"
    },
    {
      "path": "RichList__MainnetETH_holders.json",
      "size": 452,
      "modified": "2025-11-30T08:20:45.027291Z",
      "md5": "c29d42f15e7581e872f9487b12274383"
    },
    {
      "path": "githubERC20RewardsTestnet.json",
      "size": 182,
      "modified": "2025-11-30T08:20:45.028291Z",
      "md5": "f4559b4fa75caf8238c951742f6506a2"
    },
    {
      "path": "B0x_Staking_Rich_List_logs_mainnet.json",
      "size": 3546,
      "modified": "2025-11-30T08:20:50.385294Z",
      "md5": "23be9b748377b0aa069e7433e340e7d5"
    },
    {
      "path": "uu_mined_blocks_testnet.json",
      "size": 1304486,
      "modified": "2025-11-30T08:20:51.634300Z",
      "md5": "aa0488137b9865186e51e9b35e6c65e9"
    }
  ]
}