{
  "last_updated": "2026-01-11T14:50:56.544382Z",
  "source_url": "https://data.bzerox.org/mainnet/",
  "alternative_source_url": "https://b0x-token.github.io/B0x_scripts_auto/mainnetB0x/",
  "primary_available": true,
  "alternative_available": true,
  "stats": {
    "downloaded": 0,
    "updated": 11,
    "errors": 0,
    "skipped": 9
  },
  "files": [
    {
      "path": "RichList_RightsTo0xBTC_MainnetETH_holders.json",
      "size": 613,
      "modified": "2026-01-11T14:50:49.103331Z",
      "md5": "688b75a9bfbe0c932e1b46b722db9ab8"
    },
    {
      "path": "mined_blocks_testnet.json",
      "size": 278126,
      "modified": "2026-01-11T14:50:49.115331Z",
      "md5": "ec38b30e891cf22ec21ad931cfd3bb82"
    },
    {
      "path": "testnet_uniswap_v4_data.json",
      "size": 12606,
      "modified": "2026-01-11T14:50:56.224329Z",
      "md5": "3bfe57c256912c08236eda9bfdf8ca3e"
    },
    {
      "path": "price_data_bwork.json",
      "size": 6824,
      "modified": "2026-01-11T14:50:56.088329Z",
      "md5": "eaf722bd6fc1dab445327a326a4cdc44"
    },
    {
      "path": "mined_blocks_testnet.js",
      "size": 354,
      "modified": "2026-01-11T14:50:49.114331Z",
      "md5": "04f660f0973f48b1fa99b58e20d0b82d"
    },
    {
      "path": "RichList_B0x_testnet.json",
      "size": 23229,
      "modified": "2026-01-11T14:50:49.103331Z",
      "md5": "38bfddf555d337ad0c957cd4dc8b9a06"
    },
    {
      "path": "price_data_bwork_mainnetv2.json",
      "size": 6778,
      "modified": "2026-01-11T14:50:56.168329Z",
      "md5": "b81ee93eebdb5579703c153ae995ad6a"
    },
    {
      "path": "RichList_B0x_mainnet_miners.json",
      "size": 6548,
      "modified": "2026-01-11T14:50:55.106329Z",
      "md5": "c94838fe36b8750ebc45c30b8e4670a6"
    },
    {
      "path": "RichList_B0x_testnet_miners.json",
      "size": 24855,
      "modified": "2026-01-11T14:50:49.103331Z",
      "md5": "0444b8e93f71d6307837ac6dc166c973"
    },
    {
      "path": "price_data_bwork_mainnet.json",
      "size": 6856,
      "modified": "2026-01-11T14:50:49.115331Z",
      "md5": "b02c22c6dad61a16083f5ee80d68e279"
    },
    {
      "path": "atestnet_uniswap_v4_data.json",
      "size": 1084,
      "modified": "2026-01-11T14:50:49.103331Z",
      "md5": "fecdd4dea02d9e8cb3600ae50776b9e2"
    },
    {
      "path": "RichList_RightsTo0xBTC_mainnet_ETH_holders.json",
      "size": 765,
      "modified": "2026-01-11T14:50:55.257329Z",
      "md5": "681504f76da3d1ab9146e4b46d23e616"
    },
    {
      "path": "B0x_Staking_Rich_List_logs_testnet.json",
      "size": 1975,
      "modified": "2026-01-11T14:50:49.102331Z",
      "md5": "0de0ce2d7e784eb9b675c448cdbf7b61"
    },
    {
      "path": "B0x_Mainnet_APY_STATS.txt",
      "size": 632,
      "modified": "2026-01-11T14:50:49.102331Z",
      "md5": "daecadf8f5bba39bc33e64c36f0240b6"
    },
    {
      "path": "RichList_B0x_mainnet.json",
      "size": 23155,
      "modified": "2026-01-11T14:50:55.064330Z",
      "md5": "06f5fc75d06f79ee41291f167f931bde"
    },
    {
      "path": "mined_blocks_mainnet.json",
      "size": 2938930,
      "modified": "2026-01-11T14:50:56.029329Z",
      "md5": "02a1abeebc305f46dfeb71b3c9fa7aac"
    },
    {
      "path": "RichList__Mainnet_ETH_holders.json",
      "size": 908,
      "modified": "2026-01-11T14:50:55.326329Z",
      "md5": "44b7f0e1119201bb8d51def528eb693a"
    },
    {
      "path": "B0x_Mainnet_APY_STATS.json",
      "size": 668,
      "modified": "2026-01-11T14:50:54.871330Z",
      "md5": "45cacf1fe5ccdf27f3a95494aa87ffd5"
    },
    {
      "path": "mainnet_uniswap_v4_data.json",
      "size": 37331,
      "modified": "2026-01-11T14:50:55.399329Z",
      "md5": "c974d1da9d1f19e9afd4cb4f3f714e31"
    },
    {
      "path": "uniswap_v4_data_testnet.json",
      "size": 2353,
      "modified": "2026-01-11T14:50:49.115331Z",
      "md5": "cc51aadbda45ff461a7b4d6f21aa620b"
    },
    {
      "path": "RichList__MainnetETH_holders.json",
      "size": 452,
      "modified": "2026-01-11T14:50:49.103331Z",
      "md5": "c29d42f15e7581e872f9487b12274383"
    },
    {
      "path": "githubERC20RewardsTestnet.json",
      "size": 182,
      "modified": "2026-01-11T14:50:49.103331Z",
      "md5": "f4559b4fa75caf8238c951742f6506a2"
    },
    {
      "path": "B0x_Staking_Rich_List_logs_mainnet.json",
      "size": 3501,
      "modified": "2026-01-11T14:50:49.102331Z",
      "md5": "fcab6a1256323f39f531a8421a006fbe"
    },
    {
      "path": "uu_mined_blocks_testnet.json",
      "size": 1305381,
      "modified": "2026-01-11T14:50:56.542329Z",
      "md5": "3e08a1a1c29d859aae1235e8e476c8cb"
    }
  ]
}