{
  "last_updated": "2026-01-19T23:55:50.190736Z",
  "source_url": "https://data.bzerox.org/mainnet/",
  "alternative_source_url": "https://b0x-token.github.io/B0x_Scripts_auto_2/mainnetB0x/",
  "primary_available": true,
  "alternative_available": true,
  "stats": {
    "downloaded": 0,
    "updated": 8,
    "errors": 0,
    "skipped": 12
  },
  "files": [
    {
      "path": "RichList_RightsTo0xBTC_MainnetETH_holders.json",
      "size": 613,
      "modified": "2026-01-19T23:55:35.708558Z",
      "md5": "688b75a9bfbe0c932e1b46b722db9ab8"
    },
    {
      "path": "mined_blocks_testnet.json",
      "size": 278126,
      "modified": "2026-01-19T23:55:35.720558Z",
      "md5": "ec38b30e891cf22ec21ad931cfd3bb82"
    },
    {
      "path": "testnet_uniswap_v4_data.json",
      "size": 12609,
      "modified": "2026-01-19T23:55:35.721558Z",
      "md5": "e67a94cbf773129038e8aeec1c0796d6"
    },
    {
      "path": "price_data_bwork.json",
      "size": 6663,
      "modified": "2026-01-19T23:55:35.720558Z",
      "md5": "4eb45fa052dea4029d628c5b55ffebdb"
    },
    {
      "path": "mined_blocks_testnet.js",
      "size": 354,
      "modified": "2026-01-19T23:55:35.719558Z",
      "md5": "04f660f0973f48b1fa99b58e20d0b82d"
    },
    {
      "path": "RichList_B0x_testnet.json",
      "size": 23229,
      "modified": "2026-01-19T23:55:35.707558Z",
      "md5": "38bfddf555d337ad0c957cd4dc8b9a06"
    },
    {
      "path": "price_data_bwork_mainnetv2.json",
      "size": 6898,
      "modified": "2026-01-19T23:55:49.878536Z",
      "md5": "ff66689165fff291fca8b64619fa041d"
    },
    {
      "path": "RichList_B0x_mainnet_miners.json",
      "size": 6551,
      "modified": "2026-01-19T23:55:48.461538Z",
      "md5": "6cb6d033fe5497492565e57d27a573d5"
    },
    {
      "path": "RichList_B0x_testnet_miners.json",
      "size": 24855,
      "modified": "2026-01-19T23:55:35.708558Z",
      "md5": "0444b8e93f71d6307837ac6dc166c973"
    },
    {
      "path": "price_data_bwork_mainnet.json",
      "size": 6856,
      "modified": "2026-01-19T23:55:35.720558Z",
      "md5": "b02c22c6dad61a16083f5ee80d68e279"
    },
    {
      "path": "atestnet_uniswap_v4_data.json",
      "size": 1084,
      "modified": "2026-01-19T23:55:35.708558Z",
      "md5": "fecdd4dea02d9e8cb3600ae50776b9e2"
    },
    {
      "path": "RichList_RightsTo0xBTC_mainnet_ETH_holders.json",
      "size": 913,
      "modified": "2026-01-19T23:55:48.648538Z",
      "md5": "a1e68e4ef3598d1e52caa21a50632e4b"
    },
    {
      "path": "B0x_Staking_Rich_List_logs_testnet.json",
      "size": 1975,
      "modified": "2026-01-19T23:55:35.707558Z",
      "md5": "0de0ce2d7e784eb9b675c448cdbf7b61"
    },
    {
      "path": "B0x_Mainnet_APY_STATS.txt",
      "size": 632,
      "modified": "2026-01-19T23:55:35.707558Z",
      "md5": "daecadf8f5bba39bc33e64c36f0240b6"
    },
    {
      "path": "RichList_B0x_mainnet.json",
      "size": 23475,
      "modified": "2026-01-19T23:55:48.417538Z",
      "md5": "de113696ca21c23bc6ccf219ea241adf"
    },
    {
      "path": "mined_blocks_mainnet.json",
      "size": 3178236,
      "modified": "2026-01-19T23:55:49.706536Z",
      "md5": "6107dbab6f4e0daa1f12e4251a27300b"
    },
    {
      "path": "RichList__Mainnet_ETH_holders.json",
      "size": 908,
      "modified": "2026-01-19T23:55:48.738538Z",
      "md5": "853e2c032cd5f998cbb0e1b16556d883"
    },
    {
      "path": "B0x_Mainnet_APY_STATS.json",
      "size": 733,
      "modified": "2026-01-19T23:55:48.184538Z",
      "md5": "ad286746d161b6e53b228c4b8edbcd7f"
    },
    {
      "path": "mainnet_uniswap_v4_data.json",
      "size": 39743,
      "modified": "2026-01-19T23:55:48.849537Z",
      "md5": "76d423656cba231d0fdea7fd707abfbf"
    },
    {
      "path": "uniswap_v4_data_testnet.json",
      "size": 2353,
      "modified": "2026-01-19T23:55:35.721558Z",
      "md5": "cc51aadbda45ff461a7b4d6f21aa620b"
    },
    {
      "path": "RichList__MainnetETH_holders.json",
      "size": 452,
      "modified": "2026-01-19T23:55:35.708558Z",
      "md5": "c29d42f15e7581e872f9487b12274383"
    },
    {
      "path": "githubERC20RewardsTestnet.json",
      "size": 182,
      "modified": "2026-01-19T23:55:35.708558Z",
      "md5": "99b896bd95518b273ca8ec8241364880"
    },
    {
      "path": "B0x_Staking_Rich_List_logs_mainnet.json",
      "size": 3746,
      "modified": "2026-01-19T23:55:35.707558Z",
      "md5": "cd4c7cf6d492bed3ef8758ab67d8116c"
    },
    {
      "path": "uu_mined_blocks_testnet.json",
      "size": 1313619,
      "modified": "2026-01-19T23:55:35.725558Z",
      "md5": "c5d7bc79377a23433b8af0c28e945568"
    }
  ]
}