{
  "last_updated": "2025-12-27T11:45:47.271280Z",
  "source_url": "https://data.bzerox.org/mainnet/",
  "alternative_source_url": "https://b0x-token.github.io/B0x_scripts_auto/mainnetB0x/",
  "primary_available": true,
  "alternative_available": true,
  "stats": {
    "downloaded": 0,
    "updated": 8,
    "errors": 0,
    "skipped": 9
  },
  "files": [
    {
      "path": "RichList_RightsTo0xBTC_MainnetETH_holders.json",
      "size": 613,
      "modified": "2025-12-27T11:45:40.597514Z",
      "md5": "688b75a9bfbe0c932e1b46b722db9ab8"
    },
    {
      "path": "mined_blocks_testnet.json",
      "size": 278126,
      "modified": "2025-12-27T11:45:40.607514Z",
      "md5": "ec38b30e891cf22ec21ad931cfd3bb82"
    },
    {
      "path": "testnet_uniswap_v4_data.json",
      "size": 12606,
      "modified": "2025-12-27T11:45:40.608514Z",
      "md5": "70abab5d73da6fc683b5e36daf499531"
    },
    {
      "path": "price_data_bwork.json",
      "size": 6760,
      "modified": "2025-12-27T11:45:40.607514Z",
      "md5": "ea88cbc10c515a7f96af342c48c4d145"
    },
    {
      "path": "mined_blocks_testnet.js",
      "size": 354,
      "modified": "2025-12-27T11:45:40.606514Z",
      "md5": "04f660f0973f48b1fa99b58e20d0b82d"
    },
    {
      "path": "RichList_B0x_testnet.json",
      "size": 23229,
      "modified": "2025-12-27T11:45:40.596514Z",
      "md5": "38bfddf555d337ad0c957cd4dc8b9a06"
    },
    {
      "path": "RichList_B0x_mainnet_miners.json",
      "size": 6547,
      "modified": "2025-12-27T11:45:45.455549Z",
      "md5": "fd3bbda61d11d153cdaf668614f00fd8"
    },
    {
      "path": "RichList_B0x_testnet_miners.json",
      "size": 24855,
      "modified": "2025-12-27T11:45:40.597514Z",
      "md5": "0444b8e93f71d6307837ac6dc166c973"
    },
    {
      "path": "price_data_bwork_mainnet.json",
      "size": 6795,
      "modified": "2025-12-27T11:45:46.678557Z",
      "md5": "86fa0c90a50d444cc78549dc368e749a"
    },
    {
      "path": "atestnet_uniswap_v4_data.json",
      "size": 1084,
      "modified": "2025-12-27T11:45:40.597514Z",
      "md5": "fecdd4dea02d9e8cb3600ae50776b9e2"
    },
    {
      "path": "RichList_RightsTo0xBTC_mainnet_ETH_holders.json",
      "size": 765,
      "modified": "2025-12-27T11:45:45.721551Z",
      "md5": "2a0f032244d9f4e857a73e9b64d1e5b0"
    },
    {
      "path": "B0x_Staking_Rich_List_logs_testnet.json",
      "size": 1975,
      "modified": "2025-12-27T11:45:40.596514Z",
      "md5": "0de0ce2d7e784eb9b675c448cdbf7b61"
    },
    {
      "path": "RichList_B0x_mainnet.json",
      "size": 23472,
      "modified": "2025-12-27T11:45:45.385548Z",
      "md5": "b318acd253dd6423c2eefad0ed40b6df"
    },
    {
      "path": "mined_blocks_mainnet.json",
      "size": 2529723,
      "modified": "2025-12-27T11:45:46.449556Z",
      "md5": "9b34a1958ad98822ebbd2971917f1f39"
    },
    {
      "path": "RichList__Mainnet_ETH_holders.json",
      "size": 908,
      "modified": "2025-12-27T11:45:45.850552Z",
      "md5": "9e1d3acf3475658f91527ac393e015c1"
    },
    {
      "path": "mainnet_uniswap_v4_data.json",
      "size": 32508,
      "modified": "2025-12-27T11:45:45.983552Z",
      "md5": "8c105d0d48c1ea5827b701fe34c0b080"
    },
    {
      "path": "uniswap_v4_data_testnet.json",
      "size": 2353,
      "modified": "2025-12-27T11:45:40.608514Z",
      "md5": "cc51aadbda45ff461a7b4d6f21aa620b"
    },
    {
      "path": "RichList__MainnetETH_holders.json",
      "size": 452,
      "modified": "2025-12-27T11:45:40.597514Z",
      "md5": "c29d42f15e7581e872f9487b12274383"
    },
    {
      "path": "githubERC20RewardsTestnet.json",
      "size": 182,
      "modified": "2025-12-27T11:45:40.597514Z",
      "md5": "f4559b4fa75caf8238c951742f6506a2"
    },
    {
      "path": "B0x_Staking_Rich_List_logs_mainnet.json",
      "size": 3499,
      "modified": "2025-12-27T11:45:45.178547Z",
      "md5": "dddc29f79d4bda6a387135f2d26369bf"
    },
    {
      "path": "uu_mined_blocks_testnet.json",
      "size": 1305381,
      "modified": "2025-12-27T11:45:40.612514Z",
      "md5": "0dd114699fc2b7f637e46485956ed46a"
    }
  ]
}