{
  "last_updated": "2025-09-22T05:48:10.609761Z",
  "source_url": "https://data.bzerox.org/graph/",
  "stats": {
    "downloaded": 0,
    "updated": 8,
    "errors": 0,
    "skipped": 1
  },
  "files": [
    {
      "path": "price_data_bwork.json",
      "size": 6863,
      "modified": "2025-09-22T05:48:10.451519Z",
      "md5": "aca4f453dbcbff26d651191cadc6b813"
    },
    {
      "path": "RichList_B0x_testnet.json",
      "size": 1768,
      "modified": "2025-09-22T05:48:10.301518Z",
      "md5": "8c8714a29192843353934802f09b4b3d"
    },
    {
      "path": "githubERC20RewardsTestnet.json",
      "size": 182,
      "modified": "2025-09-22T05:48:05.882462Z",
      "md5": "f4559b4fa75caf8238c951742f6506a2"
    },
    {
      "path": "uu_mined_blocks_testnet.json",
      "size": 259974,
      "modified": "2025-09-22T05:48:10.608521Z",
      "md5": "b8319e7c3315ecdb7480d12bad0fb647"
    },
    {
      "path": "mined_blocks_testnet.js",
      "size": 354,
      "modified": "2025-09-22T05:48:05.882462Z",
      "md5": "04f660f0973f48b1fa99b58e20d0b82d"
    },
    {
      "path": "RichList__MainnetETH_holders.json",
      "size": 1076,
      "modified": "2025-09-22T05:48:10.386519Z",
      "md5": "cb649bb62af9431c3bd047770fc6c612"
    },
    {
      "path": "mined_blocks_testnet.json",
      "size": 278126,
      "modified": "2025-09-22T05:48:05.883462Z",
      "md5": "ec38b30e891cf22ec21ad931cfd3bb82"
    },
    {
      "path": "RichList_RightsTo0xBTC_MainnetETH_holders.json",
      "size": 770,
      "modified": "2025-09-22T05:48:10.359518Z",
      "md5": "ff1924130b6a77ec9f2714b2ac5e7a30"
    },
    {
      "path": "RichList_B0x_testnet_miners.json",
      "size": 773,
      "modified": "2025-09-22T05:48:10.329518Z",
      "md5": "91db56b4dff0a20fcde24c5d33bcbbc9"
    },
    {
      "path": "testnet_uniswap_v4_data.json",
      "size": 11354,
      "modified": "2025-09-22T05:48:10.482520Z",
      "md5": "cec38588a52dcdb089f3e8711d7baf70"
    },
    {
      "path": "B0x_Staking_Rich_List_logs_testnet.json",
      "size": 574,
      "modified": "2025-09-22T05:48:10.269517Z",
      "md5": "b9201f5c89d0cb974bcb60b6b2730aa3"
    }
  ]
}